dinky/__init__.py
dinky/dashboard_manager.py
dinky/display_configuration.py
dinky/hookspecs.py
dinky/layouts/__init__.py
dinky/layouts/column_grid_layout.py
dinky/layouts/fullscreen_layout.py
dinky/layouts/grid_layout.py
dinky/layouts/layout_configuration.py
dinky-0.2.dist-info/LICENSE
dinky-0.2.dist-info/METADATA
dinky-0.2.dist-info/WHEEL
dinky-0.2.dist-info/top_level.txt
dinky-0.2.dist-info/RECORD
