Metadata-Version: 2.1
Name: dinky
Version: 0.2
Summary: Home dashboard for the Inkyframe
Author: Julian Prester
License: MIT
Requires-Python: >=3.8
License-File: LICENSE
Requires-Dist: pydantic
Requires-Dist: pluggy
Requires-Dist: Pillow
Provides-Extra: test
Requires-Dist: pytest ; extra == 'test'
Requires-Dist: pytest-mock ; extra == 'test'
